RandAlgo/Trail_Vail.py
RandAlgo/greet.py
trivail-1.1.1.dist-info/METADATA
trivail-1.1.1.dist-info/WHEEL
trivail-1.1.1.dist-info/entry_points.txt
trivail-1.1.1.dist-info/top_level.txt
trivail-1.1.1.dist-info/RECORD
