Metadata-Version: 2.1
Name: trivail
Version: 1.1.1
Summary: A python package to display random trivia questions and answers
Home-page: https://github.com/startngstartng/Forward-RandAlgo-Victory-Wekwa
Author: Wekwa Victory Chiamaka
Author-email: victorywekwa@gmail.com
License: UNKNOWN
Platform: UNKNOWN
Requires-Dist: click
Requires-Dist: requests
